Workbook
Name Aporte: Simulador_invest!$D$19
Name Patrimônio: Simulador_invest!$D$22
Name Qtd_Anos: Simulador_invest!$D$20
Name Rendimento_carteira: Simulador_invest!$E$14

Sheet Simulador_invest
C12: Configurações
C13: Salário | E13: 100000
C14: Rendimento Carteira | E14: 0.01
C15: Sugestão de Investimento (30%) | E15: =E13*30% -> 30000
C18: Investimento Mensal
C19: Quanto investir por mês? | D19: 30000
A20: 2 | C20: Por quantos anos? | D20: 10
A21: 5 | C21: Taxa de rendimento mensal? | D21: =$E$14 -> 0.01
A22: 10 | C22: Patrimônio acumulado? | D22: =FV(Rendimento_carteira,Qtd_Anos*12,-Aporte) -> 6901160.7
A23: 20 | C23: Dividendos mensais? | D23: =Patrimônio*Rendimento_carteira -> 69011.607
A24: 30
A25: 40
C27: Cenários | E27: Dividendos
C28: Quanto eu terei em 2 anos? | D28: =FV($D$21,A20*12,-$D$19) -> 809203.95 | E28: =D28*$E$14 -> 8092.0395
C29: Quanto eu terei em 5 anos? | D29: =FV($D$21,A21*12,-$D$19) -> 2450090.1 | E29: =D29*$E$14 -> 24500.901
C30: Quanto eu terei em 10 anos? | D30: =FV($D$21,A22*12,-$D$19) -> 6901160.7 | E30: =D30*$E$14 -> 69011.607
C31: Quanto eu terei em 20 anos? | D31: =FV($D$21,A23*12,-$D$19) -> 29677661 | E31: =D31*$E$14 -> 296776.61
C32: Quanto eu terei em 30 anos? | D32: =FV($D$21,A24*12,-$D$19) -> 1.0484892e+08 | E32: =D32*$E$14 -> 1048489.2
C33: Quanto eu terei em 40 anos? | D33: =FV($D$21,A25*12,-$D$19) -> 3.5294318e+08 | E33: =D33*$E$14 -> 3529431.8
C36: Peril de Investidor | E36: Conservador
C37: VALOR A SER INVESTIDO POR MÊS | E37: =Aporte -> 30000
C41: Tipo de FII | D41: % Sugerido | E41: =E36 -> Conservador
C42: PAPEL | D42: =VLOOKUP($E$36&"-"&C42,'Tabela de apoio'!D8:G28,4,FALSE) -> 0.3 | E42: =Aporte*D42 -> 9000
C43: TIJOLO | D43: =VLOOKUP($E$36&"-"&C43,'Tabela de apoio'!D9:G29,4,FALSE) -> 0.5 | E43: =Aporte*D43 -> 15000
C44: HIBRIDOS | D44: =VLOOKUP($E$36&"-"&C44,'Tabela de apoio'!D10:G30,4,FALSE) -> 0.1 | E44: =Aporte*D44 -> 3000
C45: FOFs | D45: =VLOOKUP($E$36&"-"&C45,'Tabela de apoio'!D11:G31,4,FALSE) -> 0.1 | E45: =Aporte*D45 -> 3000
C46: DESENVOLVIMENTO | D46: =VLOOKUP($E$36&"-"&C46,'Tabela de apoio'!D12:G32,4,FALSE) -> 0 | E46: =Aporte*D46 -> 0
C47: HOTELARIA | D47: =VLOOKUP($E$36&"-"&C47,'Tabela de apoio'!D13:G33,4,FALSE) -> 0 | E47: =Aporte*D47 -> 0
C48: TOTAL GERAL | E48: =SUM(E42:E47) -> 30000

Sheet Tabela de apoio
D8: CHAVE | E8: PERFIL | F8: Tipo de FII | G8: %
D9: =E9&"-"&F9 -> Conservador-PAPEL | E9: Conservador | F9: PAPEL | G9: 0.3
D10: =E10&"-"&F10 -> Conservador-TIJOLO | E10: Conservador | F10: TIJOLO | G10: 0.5
D11: =E11&"-"&F11 -> Conservador-HIBRIDOS | E11: Conservador | F11: HIBRIDOS | G11: 0.1
D12: =E12&"-"&F12 -> Conservador-FOFs | E12: Conservador | F12: FOFs | G12: 0.1
D13: =E13&"-"&F13 -> Conservador-DESENVOLVIMENTO | E13: Conservador | F13: DESENVOLVIMENTO | G13: 0
D14: =E14&"-"&F14 -> Conservador-HOTELARIA | E14: Conservador | F14: HOTELARIA | G14: 0
D16: =E16&"-"&F16 -> Moderado-PAPEL | E16: Moderado | F16: PAPEL | G16: 0.32
D17: =E17&"-"&F17 -> Moderado-TIJOLO | E17: Moderado | F17: TIJOLO | G17: 0.35
D18: =E18&"-"&F18 -> Moderado-HIBRIDOS | E18: Moderado | F18: HIBRIDOS | G18: 0.08
D19: =E19&"-"&F19 -> Moderado-FOFs | E19: Moderado | F19: FOFs | G19: 0.05
D20: =E20&"-"&F20 -> Moderado-DESENVOLVIMENTO | E20: Moderado | F20: DESENVOLVIMENTO | G20: 0.1
D21: =E21&"-"&F21 -> Moderado-HOTELARIA | E21: Moderado | F21: HOTELARIA | G21: 0.1
... D28: =E28&"-"&F28 -> Agressivo-HOTELARIA | E28: Agressivo | F28: HOTELARIA | G28: 0.1
